procmaps-0.6.5.dist-info/METADATA
procmaps-0.6.5.dist-info/WHEEL
procmaps-0.6.5.dist-info/license_files/LICENSE
procmaps/__init__.py
procmaps/procmaps.abi3.so
procmaps-0.6.5.dist-info/RECORD
