Metadata-Version: 2.1
Name: procmaps
Version: 0.6.5
Classifier: Programming Language :: Rust
Classifier: Operating System :: POSIX :: Linux
License-File: LICENSE
Summary: Python bindings for procmaps.rs
Home-Page: https://github.com/woodruffw/procmaps.py
Author: William Woodruff <william@yossarian.net>
Author-email: William Woodruff <william@yossarian.net>
License: MIT
Requires-Python: >=3.8
Project-URL: Source Code, https://github.com/woodruffw/procmaps.py
